testipy/__init__.py
testipy/__main__.py
testipy/requirements.txt
testipy/run.py
testipy/configs/__init__.py
testipy/configs/default_config.py
testipy/configs/enums_data.py
testipy/engine/__init__.py
testipy/engine/execute_tests.py
testipy/engine/execution_logger.py
testipy/engine/execution_logger_config.yaml
testipy/engine/mylogger.py
testipy/engine/read_tests.py
testipy/engine/read_tests_utils.py
testipy/helpers/__init__.py
testipy/helpers/data_driven_testing.py
testipy/helpers/errors.py
testipy/helpers/handle_assertions.py
testipy/helpers/prettify.py
testipy/helpers/rest.py
testipy/helpers/timer.py
testipy/lib_modules/__init__.py
testipy/lib_modules/args_parser.py
testipy/lib_modules/common_methods.py
testipy/lib_modules/py_inspector.py
testipy/lib_modules/start_arguments.py
testipy/lib_modules/state_counter.py
testipy/lib_modules/textdecor.py
testipy/lib_modules/webhook_http_listener.py
testipy/lib_modules/browser_manager/__init__.py
testipy/lib_modules/browser_manager/playwright.py
testipy/lib_modules/browser_manager/selenium.py
testipy/models/__init__.py
testipy/models/attr.py
testipy/models/package_manager.py
testipy/reporter/__init__.py
testipy/reporter/report_base.py
testipy/reporter/report_interfaces.py
testipy/reporter/report_manager.py
testipy/reporter/reporters/__init__.py
testipy/reporter/reporters/df_manager.py
testipy/reporter/reporters/reporter_echo.py
testipy/reporter/reporters/reporter_excel.py
testipy/reporter/reporters/reporter_html.py
testipy/reporter/reporters/reporter_junit.py
testipy/reporter/reporters/reporter_log.py
testipy/reporter/reporters/reporter_portalio.py
testipy/reporter/reporters/reporter_portalio.yaml
testipy/reporter/reporters/reporter_slack.py
testipy/reporter/reporters/reporter_template.py
testipy/reporter/reporters/reporter_web.py
testipy/reporter/reporters/templates/jquery-3.5.1.min.js
testipy/reporter/reporters/templates/socket.io.js
testipy/reporter/reporters/templates/webreport.css
TestiPy-0.10.5.dist-info/LICENSE
TestiPy-0.10.5.dist-info/METADATA
TestiPy-0.10.5.dist-info/WHEEL
TestiPy-0.10.5.dist-info/entry_points.txt
TestiPy-0.10.5.dist-info/top_level.txt
TestiPy-0.10.5.dist-info/RECORD
