Metadata-Version: 2.1
Name: TestiPy
Version: 0.10.5
Summary: Python test selection/execution/reporting tool
Home-page: https://github.com/pjn2work/testipy
Author: Pedro Nunes
Author-email: pjn2work@google.com
Keywords: testing,reporting,behave
Classifier: Programming Language :: Python :: 3.9
Classifier: Programming Language :: Python :: 3.10
Classifier: Programming Language :: Python :: 3.11
Classifier: Programming Language :: Python :: 3.12
Classifier: License :: OSI Approved :: MIT License
Classifier: Operating System :: OS Independent
Requires-Python: >=3.9
License-File: LICENSE
Requires-Dist: wheel>=0.37
Requires-Dist: pyfiglet
Requires-Dist: tabulate
Requires-Dist: termcolor
Requires-Dist: numpy>=1.22
Requires-Dist: pandas>=1.3
Requires-Dist: bs4>=0.0.1
Requires-Dist: requests>=2.27
Requires-Dist: cryptography>=36.0
Requires-Dist: jwcrypto>=0.9
Requires-Dist: pyyaml>=5.4
Requires-Dist: tzlocal>=4.1
Requires-Dist: progressbar
Requires-Dist: tqdm>=4.61
Requires-Dist: Flask>=1.1
Requires-Dist: Flask-Session>=0.3
Requires-Dist: Flask-SocketIO>=5.0
Requires-Dist: python-socketio>=5.1
Requires-Dist: python-engineio>=4.0
Requires-Dist: gevent>=21.1.2
Requires-Dist: gevent-websocket>=0.10.1
Requires-Dist: reportportal-client>=5.0.12
Requires-Dist: xlsxwriter>=3.1
Requires-Dist: slack-sdk>=3.6
Requires-Dist: lxml>=4.6.3
Requires-Dist: webdriver-manager>=3.4.1
Requires-Dist: pyOpenSSL>=20.0.1
Requires-Dist: mss>=6.1.0
Requires-Dist: opencv-python>=4.5.3.56
Requires-Dist: playwright>=1.17
Provides-Extra: dev
Requires-Dist: pre-commit>=2.21; extra == "dev"
Requires-Dist: flake8>=3.9; extra == "dev"
